case_insensitive/__init__.py
case_insensitive/middleware.py
case_insensitive/models.py
wagtail_case_insensitive-0.1.3.dist-info/licenses/LICENSE
wagtail_case_insensitive-0.1.3.dist-info/METADATA
wagtail_case_insensitive-0.1.3.dist-info/WHEEL
wagtail_case_insensitive-0.1.3.dist-info/top_level.txt
wagtail_case_insensitive-0.1.3.dist-info/RECORD
